[{"id":"IN20190830YTBAV","type":"Feature","geometry":{"type":"Point","coordinates":[76.9952946,29.3602409]},"properties":{"name":"Riviera Home Furnishing PVT Ltd.","address":"Plot No. 235-237, Sector 29, Part 2, Huda 132103 Panipat","country_code":"IN","os_id":"IN20190830YTBAV","country_name":"India","has_approved_claim":false,"ppe_product_types":null,"ppe_contact_phone":null,"ppe_contact_email":null,"ppe_website":null,"is_closed":null}},{"id":"IN20220128MVEFM","type":"Feature","geometry":{"type":"Point","coordinates":[77.0948373,28.9306624]},"properties":{"name":"R.K. & Company","address":"1706-1707, Industrial Estate Rai, Hsiidc, Sonipat, Sonipat Haryana, India","country_code":"IN","os_id":"IN20220128MVEFM","country_name":"India","has_approved_claim":false,"ppe_product_types":null,"ppe_contact_phone":null,"ppe_contact_email":null,"ppe_website":null,"is_closed":null}},{"id":"BD2020052GCSXFJ","type":"Feature","geometry":{"type":"Point","coordinates":[90.384938,24.382688]},"properties":{"name":"Roar Fashion Ltd","address":"Dakhil Madrasa Road, Ward No: 09 Kathali, Valuka Powroshova, Valuka Mymensingh, Bangladesh","country_code":"BD","os_id":"BD2020052GCSXFJ","country_name":"Bangladesh","has_approved_claim":false,"ppe_product_types":null,"ppe_contact_phone":null,"ppe_contact_email":null,"ppe_website":null,"is_closed":null}},{"id":"SK2019083X4XN6E","type":"Feature","geometry":{"type":"Point","coordinates":[18.287297,49.0672292]},"properties":{"name":"Rona AS","address":"Schreiberova 365 2061 Lednicke Rovne","country_code":"SK","os_id":"SK2019083X4XN6E","country_name":"Slovakia","has_approved_claim":false,"ppe_product_types":null,"ppe_contact_phone":null,"ppe_contact_email":null,"ppe_website":null,"is_closed":null}},{"id":"TR2020057EFVJDD","type":"Feature","geometry":{"type":"Point","coordinates":[36.8522838,39.7170528]},"properties":{"name":"ROTA TEKS. NAK. INS. TUR. GIDA  SAN. ve TIC. LTD. STI.","address":"AYRIDAM KÖYÜ ÇORAK MEVKİ YOZGAT YOLU 4. KM  NO:88 SORGUN/YOZGAT,66700,Yozgat","country_code":"TR","os_id":"TR2020057EFVJDD","country_name":"Türkiye","has_approved_claim":false,"ppe_product_types":null,"ppe_contact_phone":null,"ppe_contact_email":null,"ppe_website":null,"is_closed":null}},{"id":"CN2019083D7V898","type":"Feature","geometry":{"type":"Point","coordinates":[121.549776,36.89184]},"properties":{"name":"Rushan longma garments co.,ltd","address":"Fuzhou Road, 7, Rushan Economic Development Zone 264500 Rushan Weihai Shandong","country_code":"CN","os_id":"CN2019083D7V898","country_name":"China","has_approved_claim":false,"ppe_product_types":null,"ppe_contact_phone":null,"ppe_contact_email":null,"ppe_website":null,"is_closed":null}},{"id":"BD2020021X22BRH","type":"Feature","geometry":{"type":"Point","coordinates":[90.5041265,23.6155967]},"properties":{"name":"RUSSEL GARMENTS","address":"Osman Tower, 56/1, S.M. Maleh Road, Narayanganj  Narayanganj","country_code":"BD","os_id":"BD2020021X22BRH","country_name":"Bangladesh","has_approved_claim":false,"ppe_product_types":null,"ppe_contact_phone":null,"ppe_contact_email":null,"ppe_website":null,"is_closed":null}},{"id":"IN2019085VQKWXE","type":"Feature","geometry":{"type":"Point","coordinates":[77.3871319,28.6127633]},"properties":{"name":"Sabs Exports","address":"C-103-105 Sector 65 Nodia 201301 Uttar Pradesh India","country_code":"IN","os_id":"IN2019085VQKWXE","country_name":"India","has_approved_claim":true,"ppe_product_types":null,"ppe_contact_phone":null,"ppe_contact_email":null,"ppe_website":null,"is_closed":null}},{"id":"TR20192595JSJDH","type":"Feature","geometry":{"type":"Point","coordinates":[30.4122917,40.7193334]},"properties":{"name":"SADIRLAR ALLIANCE TEKS A.S.","address":"Belediye Organize Sanayi Bolgesi, Inciksuyu Mahallesi, No:1 Geyve /Sakarya - Sakarya - 54700","country_code":"TR","os_id":"TR20192595JSJDH","country_name":"Türkiye","has_approved_claim":false,"ppe_product_types":null,"ppe_contact_phone":null,"ppe_contact_email":null,"ppe_website":null,"is_closed":null}},{"id":"BD2020021JH1ZCW","type":"Feature","geometry":{"type":"Point","coordinates":[90.4254248,24.0006785]},"properties":{"name":"Safaa Sweaters Ltd","address":"Begumpur, Bokran, Monipur, Bhawl Gore  Gazipur","country_code":"BD","os_id":"BD2020021JH1ZCW","country_name":"Bangladesh","has_approved_claim":false,"ppe_product_types":null,"ppe_contact_phone":null,"ppe_contact_email":null,"ppe_website":null,"is_closed":null}},{"id":"TR2021183NAC9R3","type":"Feature","geometry":{"type":"Point","coordinates":[28.961666,40.237148]},"properties":{"name":"SAFRAN TEKSTIL KONFEKSIYON SAN.VE TIC. LTD.STI","address":"Organize Sanayi Bolgesi, Sari Cadde, 1 SK, No 3 Nilufer, Bursa, Turkey","country_code":"TR","os_id":"TR2021183NAC9R3","country_name":"Türkiye","has_approved_claim":false,"ppe_product_types":null,"ppe_contact_phone":null,"ppe_contact_email":null,"ppe_website":null,"is_closed":null}},{"id":"BD20200534KPBBN","type":"Feature","geometry":{"type":"Point","coordinates":[90.634631,23.9344997]},"properties":{"name":"SAM REE DYEING (BD) LTD","address":"Factory : Mouza - 1248-268, Plot - 395-393,\nGhorashal, Polash, Dist : Norshingdi, Bangladesh. Narshingdi Dhaka","country_code":"BD","os_id":"BD20200534KPBBN","country_name":"Bangladesh","has_approved_claim":false,"ppe_product_types":null,"ppe_contact_phone":null,"ppe_contact_email":null,"ppe_website":null,"is_closed":null}},{"id":"BD201908395AJ7E","type":"Feature","geometry":{"type":"Point","coordinates":[90.3198257,23.9118537]},"properties":{"name":"Sams Attire Ltd","address":"Bhuiyan Tower, Plot No-10, Jamgora, Ashulia Road Dhaka 1349","country_code":"BD","os_id":"BD201908395AJ7E","country_name":"Bangladesh","has_approved_claim":false,"ppe_product_types":null,"ppe_contact_phone":null,"ppe_contact_email":null,"ppe_website":null,"is_closed":null}},{"id":"IN2020204YX36CH","type":"Feature","geometry":{"type":"Point","coordinates":[77.0003067,28.4376088]},"properties":{"name":"S.A.N. International (33-34)","address":"Plot No 33-34, Phase VI Udyog Vihar Sector 37 .","country_code":"IN","os_id":"IN2020204YX36CH","country_name":"India","has_approved_claim":false,"ppe_product_types":null,"ppe_contact_phone":null,"ppe_contact_email":null,"ppe_website":null,"is_closed":null}},{"id":"PK2020053DTEW80","type":"Feature","geometry":{"type":"Point","coordinates":[74.1899333,31.641105]},"properties":{"name":"Sarena Textile Industries pvt ltd","address":"22 KM, Sheikhupura Road, Lahore, Pakistan. Lahore Punjab 39321","country_code":"PK","os_id":"PK2020053DTEW80","country_name":"Pakistan","has_approved_claim":false,"ppe_product_types":null,"ppe_contact_phone":null,"ppe_contact_email":null,"ppe_website":null,"is_closed":null}},{"id":"BD2020021QD40M9","type":"Feature","geometry":{"type":"Point","coordinates":[90.40882230000001,23.9010413]},"properties":{"name":"Saturn Textiles Ltd.(Woven Division)","address":"2/6, Darul Ahsan Road, Ausepara, Tongi, Gazipur 1712 Gazipur","country_code":"BD","os_id":"BD2020021QD40M9","country_name":"Bangladesh","has_approved_claim":false,"ppe_product_types":null,"ppe_contact_phone":null,"ppe_contact_email":null,"ppe_website":null,"is_closed":null}},{"id":"BD202002171XBYV","type":"Feature","geometry":{"type":"Point","coordinates":[90.475474,23.6673064]},"properties":{"name":"SB Style CompositeLtd.","address":"Delpara,Fatullah,Narayanganj 1400 Narayanganj","country_code":"BD","os_id":"BD202002171XBYV","country_name":"Bangladesh","has_approved_claim":false,"ppe_product_types":null,"ppe_contact_phone":null,"ppe_contact_email":null,"ppe_website":null,"is_closed":null}},{"id":"IN20190831G1M5S","type":"Feature","geometry":{"type":"Point","coordinates":[77.3279886,11.1209567]},"properties":{"name":"SCM GARMENTS PVT LTD., GOBI MEGA","address":"SCM GARMENTS PVT LIMITED.,S.NO: 255/2A, VETTAIKARAN KOILMODACHUR ROAD,","country_code":"IN","os_id":"IN20190831G1M5S","country_name":"India","has_approved_claim":false,"ppe_product_types":null,"ppe_contact_phone":null,"ppe_contact_email":null,"ppe_website":null,"is_closed":null}},{"id":"IN2020053HFC7PC","type":"Feature","geometry":{"type":"Point","coordinates":[77.7396481,11.3496559]},"properties":{"name":"SCM TEXTILE PROCESSING MILLS","address":"29, C MARAPALAM ROAD, K.A.S NAGAR , KARUNGAL PALAYAM, ERODE   638003","country_code":"IN","os_id":"IN2020053HFC7PC","country_name":"India","has_approved_claim":false,"ppe_product_types":null,"ppe_contact_phone":null,"ppe_contact_email":null,"ppe_website":null,"is_closed":null}},{"id":"BD2020053J5QYSQ","type":"Feature","geometry":{"type":"Point","coordinates":[90.53282809999999,23.6978888]},"properties":{"name":"S.F. Washing Ltd.","address":"Nayabari, Kanchpur, Sonargaon, Narayangonj. Narayanganj Dhaka 1430","country_code":"BD","os_id":"BD2020053J5QYSQ","country_name":"Bangladesh","has_approved_claim":false,"ppe_product_types":null,"ppe_contact_phone":null,"ppe_contact_email":null,"ppe_website":null,"is_closed":null}},{"id":"BD2019248KH42S3","type":"Feature","geometry":{"type":"Point","coordinates":[90.3022393,23.9415728]},"properties":{"name":"Shad Fashion Ltd.","address":"Nightingale Medical College Road, Gorat, Zirabo, Ashulia, Dhaka - 1341","country_code":"BD","os_id":"BD2019248KH42S3","country_name":"Bangladesh","has_approved_claim":false,"ppe_product_types":null,"ppe_contact_phone":null,"ppe_contact_email":null,"ppe_website":null,"is_closed":null}},{"id":"IN2019086Y4ZS7J","type":"Feature","geometry":{"type":"Point","coordinates":[77.3080677,28.4331837]},"properties":{"name":"Shahi Exports (Pvt) Ltd - F2","address":"15/1 Mathura Road Faridabad Haryana, 121008, Faridabad, India","country_code":"IN","os_id":"IN2019086Y4ZS7J","country_name":"India","has_approved_claim":false,"ppe_product_types":null,"ppe_contact_phone":null,"ppe_contact_email":null,"ppe_website":null,"is_closed":null}},{"id":"IN2019108CJV3T2","type":"Feature","geometry":{"type":"Point","coordinates":[75.641312,13.878063]},"properties":{"name":"Shahi Exports Pvt Ltd Unit 36","address":"Unit-36, Sy. No. 156, Kiadb Induatrial Area, Nidige Bangalore Karnataka India","country_code":"IN","os_id":"IN2019108CJV3T2","country_name":"India","has_approved_claim":false,"ppe_product_types":null,"ppe_contact_phone":null,"ppe_contact_email":null,"ppe_website":null,"is_closed":null}},{"id":"BD20191089C8D5A","type":"Feature","geometry":{"type":"Point","coordinates":[90.2607919,23.7815408]},"properties":{"name":"Shams Styling Wears Ltd","address":"South Shyampur, Baghbari, Hemayetpur Savar Dhaka zila Bangladesh","country_code":"BD","os_id":"BD20191089C8D5A","country_name":"Bangladesh","has_approved_claim":false,"ppe_product_types":null,"ppe_contact_phone":null,"ppe_contact_email":null,"ppe_website":null,"is_closed":null}},{"id":"CN2020191T307MR","type":"Feature","geometry":{"type":"Point","coordinates":[118.627917,35.79045]},"properties":{"name":"Shandong  Hengtai Textile Co.,Ltd","address":"No.37 South-Centre Street, Yishui County, Linyi","country_code":"CN","os_id":"CN2020191T307MR","country_name":"China","has_approved_claim":false,"ppe_product_types":null,"ppe_contact_phone":null,"ppe_contact_email":null,"ppe_website":null,"is_closed":null}},{"id":"CN2019086G514SY","type":"Feature","geometry":{"type":"Point","coordinates":[117.5135425,37.50564749999999]},"properties":{"name":"Shandong Huimin Xiaofei Garment co.ltd","address":"Lizhongtiao Village, Sunwu Town, Huimin, 251799, Binzhou, China","country_code":"CN","os_id":"CN2019086G514SY","country_name":"China","has_approved_claim":false,"ppe_product_types":null,"ppe_contact_phone":null,"ppe_contact_email":null,"ppe_website":null,"is_closed":null}},{"id":"CN20221365BD1MK","type":"Feature","geometry":{"type":"Point","coordinates":[117.49897,37.028873]},"properties":{"name":"Shandong Weilian Printing & Dyeing Co., Ltd.","address":"No. 1511, 6th QiDong Road, WeiQiao Town, ZouPing County, Binzhou, Shandong","country_code":"CN","os_id":"CN20221365BD1MK","country_name":"China","has_approved_claim":false,"ppe_product_types":null,"ppe_contact_phone":null,"ppe_contact_email":null,"ppe_website":null,"is_closed":null}},{"id":"CN2019181CJBGMM","type":"Feature","geometry":{"type":"Point","coordinates":[122.069153,37.234471]},"properties":{"name":"Shandong Yinfung Hometextiles Co., Ltd","address":"No.35 Jiufa Road Economic Development Zone Wendeng City  Shandong","country_code":"CN","os_id":"CN2019181CJBGMM","country_name":"China","has_approved_claim":false,"ppe_product_types":null,"ppe_contact_phone":null,"ppe_contact_email":null,"ppe_website":null,"is_closed":null}},{"id":"CN2019266N9MR2Q","type":"Feature","geometry":{"type":"Point","coordinates":[121.9108913,30.9235605]},"properties":{"name":"Shanghai YKK Zipper Co., Ltd. Lingang Factory","address":"1258 Fei du Road, Lingang, Shanghai Shi","country_code":"CN","os_id":"CN2019266N9MR2Q","country_name":"China","has_approved_claim":false,"ppe_product_types":null,"ppe_contact_phone":null,"ppe_contact_email":null,"ppe_website":null,"is_closed":null}},{"id":"CN2019083GJK6GK","type":"Feature","geometry":{"type":"Point","coordinates":[112.794065,22.251924]},"properties":{"name":"Shantou lucy weiya fashion co.,ltd","address":"Taishan Road, Weiya Building, West 30A Street Area  Longhu Shantou Guangdong","country_code":"CN","os_id":"CN2019083GJK6GK","country_name":"China","has_approved_claim":false,"ppe_product_types":null,"ppe_contact_phone":null,"ppe_contact_email":null,"ppe_website":null,"is_closed":null}},{"id":"CN2020053GQJRP4","type":"Feature","geometry":{"type":"Point","coordinates":[120.62776,30.15715]},"properties":{"name":"Shaoxing Baoqing Printing","address":"Xinwei Road,Shaoxing,Zhejiang","country_code":"CN","os_id":"CN2020053GQJRP4","country_name":"China","has_approved_claim":false,"ppe_product_types":null,"ppe_contact_phone":null,"ppe_contact_email":null,"ppe_website":null,"is_closed":null}},{"id":"CN2019083675442","type":"Feature","geometry":{"type":"Point","coordinates":[120.2079009,30.19198]},"properties":{"name":"Shaoxing Xingming Dyeing & Tressing Co., Ltd","address":"NO:511 Binxing Road Binhai Industrial Area Shaoxing Zhejiang China","country_code":"CN","os_id":"CN2019083675442","country_name":"China","has_approved_claim":true,"ppe_product_types":null,"ppe_contact_phone":null,"ppe_contact_email":null,"ppe_website":null,"is_closed":null}},{"id":"CN2021168AVWGK9","type":"Feature","geometry":{"type":"Point","coordinates":[120.8588713,29.5773148]},"properties":{"name":"SHENGZHOU JIALAN GARMENTS&APPAREL CO.,LTD","address":"#28 HUAFA EAST ROAD,SHENGZHOU, ZHEJIANG,CHINA","country_code":"CN","os_id":"CN2021168AVWGK9","country_name":"China","has_approved_claim":false,"ppe_product_types":null,"ppe_contact_phone":null,"ppe_contact_email":null,"ppe_website":null,"is_closed":null}},{"id":"CN2022265BJ4J0Q","type":"Feature","geometry":{"type":"Point","coordinates":[120.8442203,29.5915089]},"properties":{"name":"SHENGZHOU SUNLONG GARMENT","address":"Floor2-4, Building 2 No. 28 Jinyali Road Shengzhou Zhejiang China, Shengzhou, Zhejiang, China","country_code":"CN","os_id":"CN2022265BJ4J0Q","country_name":"China","has_approved_claim":false,"ppe_product_types":null,"ppe_contact_phone":null,"ppe_contact_email":null,"ppe_website":null,"is_closed":null}},{"id":"CN20190839G0NA0","type":"Feature","geometry":{"type":"Point","coordinates":[114.27936,22.769382]},"properties":{"name":"Shenzhen New Horizon Umbrella Co Ltd","address":"No 19 Zijing Rd Pingxi Pngdi Longgang Shenzhen","country_code":"CN","os_id":"CN20190839G0NA0","country_name":"China","has_approved_claim":false,"ppe_product_types":null,"ppe_contact_phone":null,"ppe_contact_email":null,"ppe_website":null,"is_closed":null}},{"id":"VN2019266JR16H0","type":"Feature","geometry":{"type":"Point","coordinates":[106.6674484,10.348146]},"properties":{"name":"Shilla Glovis Viet Nam Co., LTD","address":"Cho Moi Hamlet, Long Hoa Commune, Go Cong Town, Tien Giang","country_code":"VN","os_id":"VN2019266JR16H0","country_name":"Vietnam","has_approved_claim":false,"ppe_product_types":null,"ppe_contact_phone":null,"ppe_contact_email":null,"ppe_website":null,"is_closed":null}},{"id":"BD20220955RGHJA","type":"Feature","geometry":{"type":"Point","coordinates":[90.2889592,23.9358004]},"properties":{"name":"Shine Embroidery Ltd","address":"198, Gazirchat, Moddhopara, Ashulia, Dhaka-1349, Bangladesh","country_code":"BD","os_id":"BD20220955RGHJA","country_name":"Bangladesh","has_approved_claim":true,"ppe_product_types":null,"ppe_contact_phone":null,"ppe_contact_email":null,"ppe_website":null,"is_closed":null}},{"id":"IN2019259N0ZK5Z","type":"Feature","geometry":{"type":"Point","coordinates":[76.0301528,30.798371]},"properties":{"name":"SHINGORA TEXTILES LTD.","address":"VPO DORAHA, TEHSIL - PAYAL, GT ROAD - LUDHIANA - 141421 - PUNJAB","country_code":"IN","os_id":"IN2019259N0ZK5Z","country_name":"India","has_approved_claim":false,"ppe_product_types":null,"ppe_contact_phone":null,"ppe_contact_email":null,"ppe_website":null,"is_closed":null}},{"id":"KR2020357E8CCTR","type":"Feature","geometry":{"type":"Point","coordinates":[126.8123263,37.3193953]},"properties":{"name":"SHIN HAN IND. CO., LTD.","address":"86 Sanseongno Danwon-gu, Ansan-city, Gyeonggi-do. Korea, 15437","country_code":"KR","os_id":"KR2020357E8CCTR","country_name":"Korea, Republic of","has_approved_claim":false,"ppe_product_types":null,"ppe_contact_phone":null,"ppe_contact_email":null,"ppe_website":null,"is_closed":null}},{"id":"VN2019083PAN70Q","type":"Feature","geometry":{"type":"Point","coordinates":[106.3171403,20.9171077]},"properties":{"name":"Shints Bvt Co., Ltd","address":"Thach Khoi Ward, Hai Duong, 170000","country_code":"VN","os_id":"VN2019083PAN70Q","country_name":"Vietnam","has_approved_claim":false,"ppe_product_types":null,"ppe_contact_phone":null,"ppe_contact_email":null,"ppe_website":null,"is_closed":null}},{"id":"VN2019085BZE6C7","type":"Feature","geometry":{"type":"Point","coordinates":[105.862313,21.460062]},"properties":{"name":"Shinwon - Ebenezer Hanoi Co., Ltd.","address":"Nguyen Gon Urban, Cai Dan Ward, Song Cong Thai Nguyen Thai Nguyen","country_code":"VN","os_id":"VN2019085BZE6C7","country_name":"Vietnam","has_approved_claim":false,"ppe_product_types":null,"ppe_contact_phone":null,"ppe_contact_email":null,"ppe_website":null,"is_closed":null}},{"id":"IN2019083791JK4","type":"Feature","geometry":{"type":"Point","coordinates":[77.3001279,28.3577012]},"properties":{"name":"Shivalik Prints Ltd","address":"Plot No 128 Sector 24 Faridabad Haryana","country_code":"IN","os_id":"IN2019083791JK4","country_name":"India","has_approved_claim":false,"ppe_product_types":null,"ppe_contact_phone":null,"ppe_contact_email":null,"ppe_website":null,"is_closed":null}},{"id":"IN2019181PG9P0J","type":"Feature","geometry":{"type":"Point","coordinates":[77.2618521,28.7889319]},"properties":{"name":"Signet Garments","address":"Plot No 5&6, Sector A.1 Tronica City Ghaziabad Uttar Pradesh","country_code":"IN","os_id":"IN2019181PG9P0J","country_name":"India","has_approved_claim":false,"ppe_product_types":null,"ppe_contact_phone":null,"ppe_contact_email":null,"ppe_website":null,"is_closed":null}},{"id":"LK2019085TT8DVM","type":"Feature","geometry":{"type":"Point","coordinates":[80.0095609,6.9566644]},"properties":{"name":"Silueta (Pvt) Limited","address":"Lot 14, Zone 01, Biyagama EPZ, Walgama, Malwana Malwana","country_code":"LK","os_id":"LK2019085TT8DVM","country_name":"Sri Lanka","has_approved_claim":false,"ppe_product_types":null,"ppe_contact_phone":null,"ppe_contact_email":null,"ppe_website":null,"is_closed":null}},{"id":"VN2019085QFWC5G","type":"Feature","geometry":{"type":"Point","coordinates":[106.2786937,20.1768392]},"properties":{"name":"Song Hong Joint Stock Company 11, 12, 13 & 14","address":"HAI PHUONG INDUSTRIAL ZONE HAI HAU DISTRICT, Nam Dinh Province, 320000","country_code":"VN","os_id":"VN2019085QFWC5G","country_name":"Vietnam","has_approved_claim":false,"ppe_product_types":null,"ppe_contact_phone":null,"ppe_contact_email":null,"ppe_website":null,"is_closed":null}},{"id":"VN2019083827T28","type":"Feature","geometry":{"type":"Point","coordinates":[105.5056075,21.1484609]},"properties":{"name":"Son Ha Garment Joint Stock Company","address":"208 LE LOI STREET, SON TAY TOWN, HA NOI CITY, 10000","country_code":"VN","os_id":"VN2019083827T28","country_name":"Vietnam","has_approved_claim":false,"ppe_product_types":null,"ppe_contact_phone":null,"ppe_contact_email":null,"ppe_website":null,"is_closed":null}},{"id":"VN202125054498E","type":"Feature","geometry":{"type":"Point","coordinates":[105.2772667,21.1124794]},"properties":{"name":"Son Ha Phu Tho Co.,Ltd","address":"HOANG XA INDUSTRIAL ZONE,THANH THUY DISTRICT, TIHN PHU THO PROVINCE, VIETNAM ,TIHN PHU THO ,TIHN PHU THO","country_code":"VN","os_id":"VN202125054498E","country_name":"Vietnam","has_approved_claim":false,"ppe_product_types":null,"ppe_contact_phone":null,"ppe_contact_email":null,"ppe_website":null,"is_closed":null}},{"id":"BD2019248XX6TVN","type":"Feature","geometry":{"type":"Point","coordinates":[90.3214135,23.9124301]},"properties":{"name":"Southern Clothings Ltd.","address":"Plot 574, Ashulia Bottola Road, Zirabo, Ashulia, Dhaka-1341","country_code":"BD","os_id":"BD2019248XX6TVN","country_name":"Bangladesh","has_approved_claim":false,"ppe_product_types":null,"ppe_contact_phone":null,"ppe_contact_email":null,"ppe_website":null,"is_closed":null}},{"id":"BD2019266XRMC1P","type":"Feature","geometry":{"type":"Point","coordinates":[90.2255279,24.0581695]},"properties":{"name":"Square Fashions Limited -Unit 2","address":"Chandana, Basan UnionDhaka By-Pass Road, Vogra, Gazipur, Dhaka","country_code":"BD","os_id":"BD2019266XRMC1P","country_name":"Bangladesh","has_approved_claim":false,"ppe_product_types":null,"ppe_contact_phone":null,"ppe_contact_email":null,"ppe_website":null,"is_closed":null}},{"id":"VN201914315CXAH","type":"Feature","geometry":{"type":"Point","coordinates":[107.0203464,10.9514768]},"properties":{"name":"Starite International Vietnam Limited","address":"Bau Xeo Industrial Park, Trang Bom District,   Bien Hoa 810000 Dong Nai Vietnam","country_code":"VN","os_id":"VN201914315CXAH","country_name":"Vietnam","has_approved_claim":false,"ppe_product_types":null,"ppe_contact_phone":null,"ppe_contact_email":null,"ppe_website":null,"is_closed":null}}]